{
  "id": "n-multi-region-official-documentation-announcements-2026-02-26-3388344",
  "source_id": "n-official-documentation-announcements",
  "canonical_url": "https://msu.io/maplestoryn/news/notices/3388344",
  "source_url": "https://msu.io/maplestoryn/news/notices/3388344",
  "external_id": "3388344",
  "title": "[UPDATED] February 26 – Magnus (Easy) Entry Guide",
  "original_title": "[UPDATED] February 26 – Magnus (Easy) Entry Guide",
  "series": "n",
  "regions": [
    "multi-region"
  ],
  "languages": [
    "en"
  ],
  "content_type": "news",
  "subcategory": "notice",
  "official": true,
  "author": "msnadmin",
  "published_at": "2026-02-26T10:10:00.000Z",
  "updated_at": null,
  "discovered_at": "2026-07-20T04:10:30.871Z",
  "last_checked": "2026-07-20T04:10:30.871Z",
  "summary": "“[UPDATED] February 26 – Magnus (Easy) Entry Guide” is an official news item from MapleStory N Official Notices on 2026-02-26. Its canonical Nexon thread and publication metadata are retained for source-backed verification.",
  "body_text": null,
  "body_markdown": null,
  "storage_mode": "summary-and-metadata",
  "tags": [
    "news",
    "notice"
  ],
  "images": [
    {
      "url": "https://dszw1qtcnsa5e.cloudfront.net/community/20250605/cf50ca00-9bc1-4b7f-beab-77133f579371/image202506051815471.png",
      "alt": null
    }
  ],
  "attachments": [],
  "related_content_ids": [],
  "related_urls": [],
  "content_hash": "0c38d09d7916b0e31081e730d6090d7f180297909e5bd8ce50f9eec068d8e2e8",
  "status": "published",
  "translation_status": "not-requested",
  "metadata": {
    "parser": "maplestory-n-official-notices",
    "api_record": true,
    "body_extractable": true,
    "fetched_at": "2026-07-20T04:12:46.828Z",
    "headline_id": "5132",
    "original_timezone": null,
    "source_time_format": "unix-epoch-seconds",
    "parser_warnings": [],
    "unconfirmed_fields": [
      "updated_at"
    ],
    "sections": [
      {
        "title": "Official publication record",
        "items": [
          "Published by msnadmin on 2026-02-26.",
          "Official classification: notice.",
          "Nexon thread ID: 3388344."
        ]
      }
    ]
  },
  "notes": null
}
